common/__init__.py
common/apps.py
common/filters.py
common/models.py
common/serializers.py
common/urls.py
common/views.py
common/viewsets.py
django_common_models-0.1.4.dist-info/DESCRIPTION.rst
django_common_models-0.1.4.dist-info/METADATA
django_common_models-0.1.4.dist-info/RECORD
django_common_models-0.1.4.dist-info/WHEEL
django_common_models-0.1.4.dist-info/metadata.json
django_common_models-0.1.4.dist-info/top_level.txt
